kerashypetune/__init__.py
kerashypetune/_classes.py
kerashypetune/kerashypetune.py
kerashypetune/utils.py
keras_hypetune-0.2.1.dist-info/LICENSE
keras_hypetune-0.2.1.dist-info/METADATA
keras_hypetune-0.2.1.dist-info/WHEEL
keras_hypetune-0.2.1.dist-info/top_level.txt
keras_hypetune-0.2.1.dist-info/RECORD
