Metadata-Version: 2.1
Name: keras-hypetune
Version: 0.2.1
Summary: A friendly python package for Keras Hyperparameters Tuning based only on NumPy and Hyperopt.
Home-page: https://github.com/cerlymarco/keras-hypetune
Author: Marco Cerliani
Author-email: cerlymarco@gmail.com
License: MIT
Platform: UNKNOWN
Requires-Python: >=3
Requires-Dist: numpy
Requires-Dist: hyperopt (==0.2.5)
